ulterpy/__init__.py
ulterpy/calendar/__init__.py
ulterpy/dataprep/__init__.py
ulterpy/elsysco/__init__.py
ulterpy/fsmod/__init__.py
ulterpy/horology/__init__.py
ulterpy/keras/__init__.py
ulterpy/matplotlib/__init__.py
ulterpy/mtpynux/__init__.py
ulterpy/numpy/__init__.py
ulterpy/onnxkit/__init__.py
ulterpy/opsys/__init__.py
ulterpy/pandas/__init__.py
ulterpy/pyplot/__init__.py
ulterpy/rtenv/__init__.py
ulterpy/sklearn/__init__.py
ulterpy/taworld/__init__.py
ulterpy/tensorflow/__init__.py
ulterpy-1.1.5.dist-info/LICENSE.txt
ulterpy-1.1.5.dist-info/METADATA
ulterpy-1.1.5.dist-info/WHEEL
ulterpy-1.1.5.dist-info/top_level.txt
ulterpy-1.1.5.dist-info/RECORD
