Metadata-Version: 2.1
Name: ulterpy
Version: 1.1.5
Summary: ULTRA ERGONOMIC PYTHON
Home-page: https://github.com/pythonsystem/ulterpy
Author: Open Liberal
License: MIT
License-File: LICENSE.txt
Requires-Dist: ipython ==8.12.3
Requires-Dist: pyzmq ==25.1.2
Requires-Dist: requests ==2.32.3
Requires-Dist: jupyter ==1.0.0
Requires-Dist: elsysco ==1.0.2
Requires-Dist: mtpynux ==1.0.8
Requires-Dist: tensorflow ==2.13.1
Requires-Dist: keras ==2.13.1
Requires-Dist: matplotlib ==3.7.5
Requires-Dist: numpy ==1.24.3
Requires-Dist: pandas ==2.0.3
Requires-Dist: taworld ==1.0.5
